<!DOCTYPE ui:UiBinder SYSTEM "http://dl.google.com/gwt/DTD/xhtml.ent">
<ui:UiBinder xmlns:ui="urn:ui:com.google.gwt.uibinder"
	xmlns:g="urn:import:com.google.gwt.user.client.ui" xmlns:c="urn:import:org.openstack.ui.client.compute.common">
	<ui:style>
		
	</ui:style>
	<g:HeaderPanel width="300px" height="200px">
		<g:HTMLPanel>
			<div class="modal-header" style="margin-bottom: 15px">
				<g:Anchor ui:field="close" styleName="close">×</g:Anchor>
				<h3>Change Password</h3>
			</div>
		</g:HTMLPanel>
		<g:ResizeLayoutPanel height="100%">
			<g:HTMLPanel>
				<table>
					<tobdy>
						<tr>
							<td>New Administration Password</td>
						</tr>
						<tr>
							<td><g:PasswordTextBox ui:field="adminPass" /></td>
						</tr>
					</tobdy>
				</table>
			</g:HTMLPanel>
			
		</g:ResizeLayoutPanel>
		<g:HTMLPanel ui:field="footer" styleName="modal-footer">
			<g:Button ui:field="execute" styleName="btn">Change Password</g:Button>
			<g:Button ui:field="cancel" styleName="btn">Cancel</g:Button>
		</g:HTMLPanel>
	</g:HeaderPanel>
</ui:UiBinder> 